aws_cli_bedrock/__init__.py
aws_cli_bedrock/cli_creactor.py
aws_cli_bedrock/cli_reactor.py
aws_cli_bedrock/test/__init__.py
aws_cli_bedrock/test/test_cli_creator.py
aws_cli_bedrock/test/test_cli_reactor.py
acmd-0.1.4.dist-info/LICENSE
acmd-0.1.4.dist-info/METADATA
acmd-0.1.4.dist-info/WHEEL
acmd-0.1.4.dist-info/entry_points.txt
acmd-0.1.4.dist-info/top_level.txt
acmd-0.1.4.dist-info/RECORD
